obynverifications/__init__.py
obynverifications/api.py
obynverifications/config.py
obynverifications/models.py
obynverifications/tasks.py
obynverifications/utils.py
obynverifications/verify.py
obyn_obynverification-0.1.0.dist-info/METADATA
obyn_obynverification-0.1.0.dist-info/WHEEL
obyn_obynverification-0.1.0.dist-info/top_level.txt
obyn_obynverification-0.1.0.dist-info/RECORD
